wikidot/__init__.py
wikidot/py.typed
wikidot/common/__init__.py
wikidot/common/decorators.py
wikidot/common/exceptions.py
wikidot/common/logger.py
wikidot/connector/__init__.py
wikidot/connector/ajax.py
wikidot/module/__init__.py
wikidot/module/auth.py
wikidot/module/client.py
wikidot/module/forum_category.py
wikidot/module/forum_post.py
wikidot/module/forum_post_revision.py
wikidot/module/forum_thread.py
wikidot/module/page.py
wikidot/module/page_file.py
wikidot/module/page_revision.py
wikidot/module/page_source.py
wikidot/module/page_votes.py
wikidot/module/private_message.py
wikidot/module/site.py
wikidot/module/site_application.py
wikidot/module/site_member.py
wikidot/module/user.py
wikidot/util/__init__.py
wikidot/util/async_helper.py
wikidot/util/http.py
wikidot/util/quick_module.py
wikidot/util/requestutil.py
wikidot/util/stringutil.py
wikidot/util/parser/__init__.py
wikidot/util/parser/odate.py
wikidot/util/parser/user.py
wikidot/util/table/__init__.py
wikidot/util/table/char_table.py
wikidot-4.3.1.dist-info/METADATA
wikidot-4.3.1.dist-info/WHEEL
wikidot-4.3.1.dist-info/licenses/LICENSE
wikidot-4.3.1.dist-info/RECORD
