Metadata-Version: 2.4
Name: wikidot
Version: 4.3.1
Summary: Wikidot Utility Library
Project-URL: Homepage, https://github.com/ukwhatn/wikidot.py
Project-URL: Bug Tracker, https://github.com/ukwhatn/wikidot.py/issues
Author-email: ukwhatn <ukwhatn@gmail.com>
License-File: LICENSE
Classifier: Development Status :: 3 - Alpha
Classifier: License :: OSI Approved :: MIT License
Classifier: Programming Language :: Python :: 3.10
Classifier: Programming Language :: Python :: 3.11
Classifier: Programming Language :: Python :: 3.12
Classifier: Programming Language :: Python :: 3.13
Classifier: Programming Language :: Python :: 3.14
Requires-Python: >=3.10
Requires-Dist: beautifulsoup4<4.15.0,>=4.12.2
Requires-Dist: httpx<0.29,>=0.25
Requires-Dist: lxml<6.1.0,>=4.9.3
Requires-Dist: typing-extensions>=4.5.0; python_version < '3.12'
Provides-Extra: build
Requires-Dist: build; extra == 'build'
Requires-Dist: twine; extra == 'build'
Provides-Extra: dev
Requires-Dist: pre-commit>=3.6.0; extra == 'dev'
Provides-Extra: format
Requires-Dist: ruff; extra == 'format'
Provides-Extra: lint
Requires-Dist: lxml-stubs; extra == 'lint'
Requires-Dist: mypy; extra == 'lint'
Requires-Dist: ruff; extra == 'lint'
Requires-Dist: types-beautifulsoup4; extra == 'lint'
Provides-Extra: test
Requires-Dist: pytest-asyncio>=0.23.0; extra == 'test'
Requires-Dist: pytest-cov>=4.1.0; extra == 'test'
Requires-Dist: pytest-httpx>=0.35.0; extra == 'test'
Requires-Dist: pytest>=8.0.0; extra == 'test'
